faceemotionrecognition/main.py
faceemotionrecognition/trained_model.pt
faceemotionrecognition/yolo11n-seg.pt
faceemotionrecognition-1.2.2.dist-info/LICENSE
faceemotionrecognition-1.2.2.dist-info/METADATA
faceemotionrecognition-1.2.2.dist-info/WHEEL
faceemotionrecognition-1.2.2.dist-info/entry_points.txt
faceemotionrecognition-1.2.2.dist-info/top_level.txt
faceemotionrecognition-1.2.2.dist-info/RECORD
